{
  "code": "C4337",
  "name": "Mantle Cell Lymphoma",
  "terminology": "ncit",
  "version": "25.11d",
  "conceptStatus": "DEFAULT",
  "leaf": false,
  "active": true,
  "synonyms": [
    {
      "name": "Mantle Cell Lymphoma",
      "termType": "SY",
      "type": "FULL_SYN",
      "source": "caDSR"
    },
    {
      "name": "Mantle Cell Lymphoma",
      "termType": "PT",
      "type": "FULL_SYN",
      "source": "Cellosaurus"
    },
    {
      "name": "Mantle Cell Lymphoma",
      "termType": "PT",
      "type": "FULL_SYN",
      "source": "CPTAC"
    },
    {
      "name": "Mantle cell lymphoma",
      "termType": "PT",
      "type": "FULL_SYN",
      "source": "CTEP",
      "code": "10026799",
      "subSource": "SDC"
    },
    {
      "name": "Mantle Cell Lymphoma",
      "termType": "DN",
      "type": "FULL_SYN",
      "source": "CTRP"
    },
    {
      "name": "Mantle zone lymphoma",
      "termType": "PT",
      "type": "FULL_SYN",
      "source": "GDC"
    },
    {
      "name": "Mantle cell lymphoma, unspecified site",
      "termType": "PT",
      "type": "FULL_SYN",
      "source": "mCode",
      "code": "C83.10",
      "subSource": "ICD-10 CM"
    },
    {
      "name": "mantle cell lymphoma",
      "termType": "PT",
      "type": "FULL_SYN",
      "source": "NCI-GLOSS",
      "code": "CDR0000445048"
    },
    {
      "name": "Classical Mantle Cell Lymphoma",
      "termType": "SY",
      "type": "FULL_SYN",
      "source": "NCI"
    },
    {
      "name": "Mantle Cell Lymphoma",
      "termType": "PT",
      "type": "FULL_SYN",
      "source": "NCI"
    },
    {
      "name": "Mantle Zone Lymphoma",
      "termType": "AQS",
      "type": "FULL_SYN",
      "source": "NCI"
    },
    {
      "name": "MCL",
      "termType": "AB",
      "type": "FULL_SYN",
      "source": "NCI"
    },
    {
      "name": "Mantle Cell Lymphoma",
      "type": "Display_Name"
    },
    {
      "name": "Mantle Cell Lymphoma",
      "type": "Preferred_Name"
    }
  ],
  "definitions": [
    {
      "definition": "A non-Hodgkin lymphoma composed of small to medium sized B-lymphocytes (centrocytes). Most patients present with advanced stage disease with lymphadenopathy, hepatosplenomegaly, and bone marrow involvement. The gastrointestinal tract is the most commonly affected extranodal site by this type of non-Hodgkin lymphoma. The vast majority of cases express the t(11;14)(q13;q32) resulting in the rearrangement of the BCL-1 gene and the overexpression of cyclin D1 mRNA.",
      "type": "DEFINITION",
      "source": "NCI"
    },
    {
      "definition": "An aggressive (fast-growing) type of B-cell non-Hodgkin lymphoma that usually occurs in middle-aged or older adults. It is marked by small- to medium-size cancer cells that may be in the lymph nodes, spleen, bone marrow, blood, and gastrointestinal system.",
      "type": "ALT_DEFINITION",
      "source": "NCI-GLOSS"
    }
  ],
  "properties": [
    {
      "code": "P322",
      "type": "Contributing_Source",
      "value": "Cellosaurus"
    },
    {
      "code": "P322",
      "type": "Contributing_Source",
      "value": "CPTAC"
    },
    {
      "code": "P322",
      "type": "Contributing_Source",
      "value": "CTEP"
    },
    {
      "code": "P322",
      "type": "Contributing_Source",
      "value": "CTRP"
    },
    {
      "code": "P322",
      "type": "Contributing_Source",
      "value": "GDC"
    },
    {
      "code": "P322",
      "type": "Contributing_Source",
      "value": "mCode"
    },
    {
      "code": "P334",
      "type": "ICD-O-3_Code",
      "value": "9673/3"
    },
    {
      "code": "P366",
      "type": "Legacy Concept Name",
      "value": "Mantle_Cell_Lymphoma"
    },
    {
      "code": "P375",
      "type": "Maps_To",
      "value": "9673/3"
    },
    {
      "code": "P375",
      "type": "Maps_To",
      "value": "Malignant lymphoma, lymphocytic, intermediate differentiation, diffuse"
    },
    {
      "code": "P375",
      "type": "Maps_To",
      "value": "Mantle cell lymphoma"
    },
    {
      "code": "P375",
      "type": "Maps_To",
      "value": "Mantle cell lymphoma (Includes all variants blastic, pleomorphic, small cell)"
    },
    {
      "code": "P375",
      "type": "Maps_To",
      "value": "Mantle cell lymphoma, extranodal and solid organ sites"
    },
    {
      "code": "P375",
      "type": "Maps_To",
      "value": "Mantle cell lymphoma, lymph nodes of multiple sites"
    },
    {
      "code": "P375",
      "type": "Maps_To",
      "value": "Mantle cell lymphoma, unspecified site"
    },
    {
      "code": "P375",
      "type": "Maps_To",
      "value": "Mantle cell lymphoma, unspecified site, extranodal and solid organ sites"
    },
    {
      "code": "P375",
      "type": "Maps_To",
      "value": "Mantle zone lymphoma"
    },
    {
      "code": "P363",
      "type": "Neoplastic_Status",
      "value": "Malignant"
    },
    {
      "code": "P106",
      "type": "Semantic_Type",
      "value": "Neoplastic Process"
    },
    {
      "code": "P207",
      "type": "UMLS_CUI",
      "value": "C0334634"
    }
  ],
  "children": [
    {
      "code": "C217100",
      "name": "Advanced Mantle Cell Lymphoma",
      "leaf": true
    },
    {
      "code": "C7229",
      "name": "Blastoid Variant Mantle Cell Lymphoma",
      "leaf": true
    },
    {
      "code": "C96505",
      "name": "Colorectal Mantle Cell Lymphoma",
      "leaf": false
    },
    {
      "code": "C45266",
      "name": "Cutaneous Mantle Cell Lymphoma",
      "leaf": true
    },
    {
      "code": "C200685",
      "name": "Cyclin D1-Negative Mantle Cell Lymphoma",
      "leaf": false
    },
    {
      "code": "C199481",
      "name": "Cyclin D1-Positive Mantle Cell Lymphoma",
      "leaf": true
    },
    {
      "code": "C27440",
      "name": "Gastric Mantle Cell Lymphoma",
      "leaf": true
    },
    {
      "code": "C202925",
      "name": "Head and Neck Mantle Cell Lymphoma",
      "leaf": false
    },
    {
      "code": "C141257",
      "name": "Mantle Cell Lymphoma by Ann Arbor Stage",
      "leaf": false
    },
    {
      "code": "C39747",
      "name": "Pleomorphic Variant Mantle Cell Lymphoma",
      "leaf": true
    },
    {
      "code": "C161604",
      "name": "Prostate Mantle Cell Lymphoma",
      "leaf": true
    },
    {
      "code": "C8489",
      "name": "Recurrent Mantle Cell Lymphoma",
      "leaf": true
    },
    {
      "code": "C8862",
      "name": "Refractory Mantle Cell Lymphoma",
      "leaf": true
    },
    {
      "code": "C27441",
      "name": "Small Intestinal Mantle Cell Lymphoma",
      "leaf": true
    },
    {
      "code": "C7306",
      "name": "Splenic Mantle Cell Lymphoma",
      "leaf": true
    }
  ],
  "parents": [
    {
      "code": "C7056",
      "name": "Mature B-Cell Non-Hodgkin Lymphoma"
    }
  ],
  "associations": [
    {
      "type": "Concept_In_Subset",
      "relatedCode": "C165258",
      "relatedName": "Cellosaurus Disease Terminology"
    },
    {
      "type": "Concept_In_Subset",
      "relatedCode": "C158520",
      "relatedName": "CPTAC Codelists Terminology"
    },
    {
      "type": "Concept_In_Subset",
      "relatedCode": "C156966",
      "relatedName": "CPTAC Neoplasms Codelist"
    },
    {
      "type": "Concept_In_Subset",
      "relatedCode": "C156952",
      "relatedName": "CPTAC Terminology"
    },
    {
      "type": "Concept_In_Subset",
      "relatedCode": "C118168",
      "relatedName": "CTRP Disease Terminology"
    },
    {
      "type": "Concept_In_Subset",
      "relatedCode": "C116977",
      "relatedName": "CTRP Terminology"
    },
    {
      "type": "Concept_In_Subset",
      "relatedCode": "C157711",
      "relatedName": "GDC Terminology"
    },
    {
      "type": "Concept_In_Subset",
      "relatedCode": "C177537",
      "relatedName": "GDC Value Terminology"
    },
    {
      "type": "Is_Value_For_GDC_Property",
      "relatedCode": "C176985",
      "relatedName": "Histology ICD-O Morphology Code"
    },
    {
      "type": "Is_Value_For_GDC_Property",
      "relatedCode": "C177621",
      "relatedName": "ICD-O-3 Morphology Term Diagnosis Question"
    },
    {
      "type": "Concept_In_Subset",
      "relatedCode": "C168658",
      "relatedName": "Mapped ICDO3.1 Morphology PT Terminology"
    },
    {
      "type": "Concept_In_Subset",
      "relatedCode": "C168657",
      "relatedName": "Mapped ICDO3.1 Morphology Terminology"
    },
    {
      "type": "Concept_In_Subset",
      "relatedCode": "C168655",
      "relatedName": "Mapped ICDO3.1 Terminology"
    },
    {
      "type": "Concept_In_Subset",
      "relatedCode": "C168662",
      "relatedName": "Mapped ICDO3.2 Morphology PT Terminology"
    },
    {
      "type": "Concept_In_Subset",
      "relatedCode": "C168661",
      "relatedName": "Mapped ICDO3.2 Morphology Terminology"
    },
    {
      "type": "Concept_In_Subset",
      "relatedCode": "C168656",
      "relatedName": "Mapped ICDO3.2 Terminology"
    },
    {
      "type": "Concept_In_Subset",
      "relatedCode": "C193249",
      "relatedName": "mCode Cancer Disorder Value Set"
    },
    {
      "type": "Concept_In_Subset",
      "relatedCode": "C193175",
      "relatedName": "mCode Elixhauser Lymphoma Value Set"
    },
    {
      "type": "Concept_In_Subset",
      "relatedCode": "C193248",
      "relatedName": "mCode Primary Cancer Disorder Value Set"
    },
    {
      "type": "Concept_In_Subset",
      "relatedCode": "C193231",
      "relatedName": "mCode Primary Malignant Neoplasm Disorder Value Set"
    },
    {
      "type": "Concept_In_Subset",
      "relatedCode": "C193006",
      "relatedName": "mCode Terminology"
    },
    {
      "type": "Concept_In_Subset",
      "relatedCode": "C103133",
      "relatedName": "NCI CTEP SDC Non-Hodgkin Lymphoma Sub-Category Terminology"
    },
    {
      "type": "Concept_In_Subset",
      "relatedCode": "C102905",
      "relatedName": "NCI CTEP Simplified Disease Classification Terminology"
    },
    {
      "type": "Concept_In_Subset",
      "relatedCode": "C126659",
      "relatedName": "NCIt Neoplasm Core Terminology"
    }
  ],
  "inverseAssociations": [
    {
      "type": "Has_GDC_Value",
      "relatedCode": "C176985",
      "relatedName": "Histology ICD-O Morphology Code"
    },
    {
      "type": "Has_GDC_Value",
      "relatedCode": "C177621",
      "relatedName": "ICD-O-3 Morphology Term Diagnosis Question"
    }
  ],
  "roles": [
    {
      "type": "Disease_Has_Abnormal_Cell",
      "relatedCode": "C36725",
      "relatedName": "Abnormal Lymphocyte"
    },
    {
      "type": "Disease_Has_Normal_Cell_Origin",
      "relatedCode": "C12474",
      "relatedName": "B-Lymphocyte"
    },
    {
      "type": "Disease_Excludes_Finding",
      "relatedCode": "C36122",
      "relatedName": "Benign Cellular Infiltrate"
    },
    {
      "type": "Disease_Has_Molecular_Abnormality",
      "relatedCode": "C36443",
      "relatedName": "Clonal Immunoglobulin Gene Rearrangement"
    },
    {
      "type": "Disease_Has_Molecular_Abnormality",
      "relatedCode": "C36444",
      "relatedName": "Clonal Immunoglobulin Heavy Chain Gene Rearrangement"
    },
    {
      "type": "Disease_Has_Molecular_Abnormality",
      "relatedCode": "C36451",
      "relatedName": "Clonal Immunoglobulin Kappa Light Chain Gene Rearrangement"
    },
    {
      "type": "Disease_Has_Molecular_Abnormality",
      "relatedCode": "C36452",
      "relatedName": "Clonal Immunoglobulin Lambda Light Chain Gene Rearrangement"
    },
    {
      "type": "Disease_Has_Associated_Anatomic_Site",
      "relatedCode": "C41165",
      "relatedName": "Hematopoietic and Lymphatic System"
    },
    {
      "type": "Disease_Has_Primary_Anatomic_Site",
      "relatedCode": "C41165",
      "relatedName": "Hematopoietic and Lymphatic System"
    },
    {
      "type": "Disease_Has_Normal_Cell_Origin",
      "relatedCode": "C32725",
      "relatedName": "Hematopoietic and Lymphoid Cell"
    },
    {
      "type": "Disease_Has_Normal_Tissue_Origin",
      "relatedCode": "C41168",
      "relatedName": "Hematopoietic and Lymphoid Tissue"
    },
    {
      "type": "Disease_May_Have_Finding",
      "relatedCode": "C50764",
      "relatedName": "Lymphadenopathy"
    },
    {
      "type": "Disease_Has_Primary_Anatomic_Site",
      "relatedCode": "C12746",
      "relatedName": "Lymphatic System"
    },
    {
      "type": "Disease_Excludes_Abnormal_Cell",
      "relatedCode": "C37027",
      "relatedName": "Lymphocyte Predominant Cell"
    },
    {
      "type": "Disease_Has_Normal_Cell_Origin",
      "relatedCode": "C12535",
      "relatedName": "Lymphocyte"
    },
    {
      "type": "Disease_Has_Normal_Tissue_Origin",
      "relatedCode": "C13049",
      "relatedName": "Lymphoid Tissue"
    },
    {
      "type": "Disease_Has_Abnormal_Cell",
      "relatedCode": "C12917",
      "relatedName": "Malignant Cell"
    },
    {
      "type": "Disease_Has_Finding",
      "relatedCode": "C36115",
      "relatedName": "Malignant Cellular Infiltrate"
    },
    {
      "type": "Disease_Has_Normal_Tissue_Origin",
      "relatedCode": "C33053",
      "relatedName": "Mantle Zone"
    },
    {
      "type": "Disease_Has_Normal_Cell_Origin",
      "relatedCode": "C33058",
      "relatedName": "Mature B-Lymphocyte"
    },
    {
      "type": "Disease_Excludes_Normal_Cell_Origin",
      "relatedCode": "C12549",
      "relatedName": "Myeloid Cell"
    },
    {
      "type": "Disease_Has_Abnormal_Cell",
      "relatedCode": "C38640",
      "relatedName": "Neoplastic B-Lymphocyte"
    },
    {
      "type": "Disease_Has_Abnormal_Cell",
      "relatedCode": "C12922",
      "relatedName": "Neoplastic Cell"
    },
    {
      "type": "Disease_Has_Abnormal_Cell",
      "relatedCode": "C37060",
      "relatedName": "Neoplastic Hematopoietic and Lymphoid Cell"
    },
    {
      "type": "Disease_Has_Abnormal_Cell",
      "relatedCode": "C36988",
      "relatedName": "Neoplastic Lymphocyte"
    },
    {
      "type": "Disease_Has_Abnormal_Cell",
      "relatedCode": "C45310",
      "relatedName": "Neoplastic Small to Medium-Sized B-Lymphocyte Resembling a Centrocyte"
    },
    {
      "type": "Disease_Excludes_Abnormal_Cell",
      "relatedCode": "C39566",
      "relatedName": "Neoplastic T-Lymphocyte and Neoplastic Natural Killer Cell"
    },
    {
      "type": "Disease_Has_Normal_Cell_Origin",
      "relatedCode": "C38332",
      "relatedName": "Peripheral B-Lymphocyte of Inner Mantle Zone"
    },
    {
      "type": "Disease_Excludes_Normal_Cell_Origin",
      "relatedCode": "C12486",
      "relatedName": "Plasma Cell"
    },
    {
      "type": "Disease_Excludes_Normal_Cell_Origin",
      "relatedCode": "C33931",
      "relatedName": "Precursor B-Lymphoblast"
    },
    {
      "type": "Disease_Excludes_Abnormal_Cell",
      "relatedCode": "C12660",
      "relatedName": "Reed-Sternberg Cell"
    }
  ],
  "inverseRoles": [
    {
      "type": "Regimen_Has_Accepted_Use_For_Disease",
      "relatedCode": "C63779",
      "relatedName": "EPOCH Regimen"
    },
    {
      "type": "Regimen_Has_Accepted_Use_For_Disease",
      "relatedCode": "C63461",
      "relatedName": "EPOCH-R Regimen"
    },
    {
      "type": "Disease_May_Have_Associated_Disease",
      "relatedCode": "C4339",
      "relatedName": "Multifocal Lymphomatous Polyposis"
    },
    {
      "type": "Regimen_Has_Accepted_Use_For_Disease",
      "relatedCode": "C9760",
      "relatedName": "R-CHOP Regimen"
    },
    {
      "type": "Regimen_Has_Accepted_Use_For_Disease",
      "relatedCode": "C156246",
      "relatedName": "R-CHOP-Methotrexate Regimen"
    },
    {
      "type": "Regimen_Has_Accepted_Use_For_Disease",
      "relatedCode": "C201147",
      "relatedName": "R-maxi-CHOP Regimen"
    }
  ],
  "history": [
    {
      "code": "C4337",
      "action": "create",
      "date": "2003-08-12"
    },
    {
      "code": "C4337",
      "action": "modify",
      "date": "2003-10-31"
    },
    {
      "code": "C4337",
      "action": "modify",
      "date": "2003-12-30"
    },
    {
      "code": "C4337",
      "action": "modify",
      "date": "2004-03-30"
    },
    {
      "code": "C4337",
      "action": "modify",
      "date": "2004-04-30"
    },
    {
      "code": "C4337",
      "action": "modify",
      "date": "2004-05-28"
    },
    {
      "code": "C4337",
      "action": "modify",
      "date": "2004-06-25"
    },
    {
      "code": "C4337",
      "action": "modify",
      "date": "2005-03-30"
    },
    {
      "code": "C4337",
      "action": "modify",
      "date": "2006-12-01"
    },
    {
      "code": "C4337",
      "action": "modify",
      "date": "2007-03-30"
    },
    {
      "code": "C4337",
      "action": "modify",
      "date": "2007-05-25"
    },
    {
      "code": "C4337",
      "action": "modify",
      "date": "2007-06-28"
    },
    {
      "code": "C4337",
      "action": "modify",
      "date": "2009-04-06"
    },
    {
      "code": "C39746",
      "action": "retire",
      "date": "2009-04-20",
      "replacementCode": "C4337",
      "replacementName": "Mantle Cell Lymphoma"
    },
    {
      "code": "C4337",
      "action": "modify",
      "date": "2009-10-27"
    },
    {
      "code": "C4337",
      "action": "modify",
      "date": "2009-11-23"
    },
    {
      "code": "C4337",
      "action": "modify",
      "date": "2010-11-08"
    },
    {
      "code": "C4337",
      "action": "modify",
      "date": "2010-11-15"
    },
    {
      "code": "C4337",
      "action": "modify",
      "date": "2010-11-22"
    },
    {
      "code": "C4337",
      "action": "modify",
      "date": "2010-11-29"
    },
    {
      "code": "C4337",
      "action": "modify",
      "date": "2010-12-06"
    },
    {
      "code": "C4337",
      "action": "modify",
      "date": "2010-12-13"
    },
    {
      "code": "C4337",
      "action": "modify",
      "date": "2010-12-27"
    },
    {
      "code": "C4337",
      "action": "modify",
      "date": "2011-01-03"
    },
    {
      "code": "C4337",
      "action": "modify",
      "date": "2011-01-10"
    },
    {
      "code": "C4337",
      "action": "modify",
      "date": "2011-01-17"
    },
    {
      "code": "C4337",
      "action": "modify",
      "date": "2011-01-24"
    },
    {
      "code": "C4337",
      "action": "modify",
      "date": "2011-01-31"
    },
    {
      "code": "C4337",
      "action": "modify",
      "date": "2011-08-22"
    },
    {
      "code": "C4337",
      "action": "modify",
      "date": "2011-12-27"
    },
    {
      "code": "C4337",
      "action": "modify",
      "date": "2012-09-24"
    },
    {
      "code": "C4337",
      "action": "modify",
      "date": "2012-10-01"
    },
    {
      "code": "C4337",
      "action": "modify",
      "date": "2012-10-09"
    },
    {
      "code": "C4337",
      "action": "modify",
      "date": "2012-10-15"
    },
    {
      "code": "C4337",
      "action": "modify",
      "date": "2012-10-22"
    },
    {
      "code": "C4337",
      "action": "modify",
      "date": "2012-10-31"
    },
    {
      "code": "C4337",
      "action": "modify",
      "date": "2012-11-05"
    },
    {
      "code": "C4337",
      "action": "modify",
      "date": "2012-11-13"
    },
    {
      "code": "C4337",
      "action": "modify",
      "date": "2012-11-19"
    },
    {
      "code": "C4337",
      "action": "modify",
      "date": "2012-11-26"
    },
    {
      "code": "C4337",
      "action": "modify",
      "date": "2012-12-03"
    },
    {
      "code": "C4337",
      "action": "modify",
      "date": "2012-12-10"
    },
    {
      "code": "C4337",
      "action": "modify",
      "date": "2012-12-17"
    },
    {
      "code": "C4337",
      "action": "modify",
      "date": "2012-12-28"
    },
    {
      "code": "C4337",
      "action": "modify",
      "date": "2013-01-07"
    },
    {
      "code": "C4337",
      "action": "modify",
      "date": "2013-01-14"
    },
    {
      "code": "C4337",
      "action": "modify",
      "date": "2013-01-23"
    },
    {
      "code": "C4337",
      "action": "modify",
      "date": "2013-02-04"
    },
    {
      "code": "C4337",
      "action": "modify",
      "date": "2013-02-11"
    },
    {
      "code": "C4337",
      "action": "modify",
      "date": "2013-02-19"
    },
    {
      "code": "C4337",
      "action": "modify",
      "date": "2013-02-25"
    },
    {
      "code": "C4337",
      "action": "modify",
      "date": "2013-03-04"
    },
    {
      "code": "C4337",
      "action": "modify",
      "date": "2013-03-11"
    },
    {
      "code": "C4337",
      "action": "modify",
      "date": "2013-03-18"
    },
    {
      "code": "C4337",
      "action": "modify",
      "date": "2013-03-25"
    },
    {
      "code": "C4337",
      "action": "modify",
      "date": "2013-04-01"
    },
    {
      "code": "C4337",
      "action": "modify",
      "date": "2013-04-08"
    },
    {
      "code": "C4337",
      "action": "modify",
      "date": "2013-04-15"
    },
    {
      "code": "C4337",
      "action": "modify",
      "date": "2013-04-22"
    },
    {
      "code": "C4337",
      "action": "modify",
      "date": "2013-04-29"
    },
    {
      "code": "C4337",
      "action": "modify",
      "date": "2013-05-06"
    },
    {
      "code": "C4337",
      "action": "modify",
      "date": "2013-05-13"
    },
    {
      "code": "C4337",
      "action": "modify",
      "date": "2013-05-20"
    },
    {
      "code": "C4337",
      "action": "modify",
      "date": "2013-05-28"
    },
    {
      "code": "C4337",
      "action": "modify",
      "date": "2013-06-03"
    },
    {
      "code": "C4337",
      "action": "modify",
      "date": "2013-06-10"
    },
    {
      "code": "C4337",
      "action": "modify",
      "date": "2013-06-17"
    },
    {
      "code": "C4337",
      "action": "modify",
      "date": "2013-06-24"
    },
    {
      "code": "C4337",
      "action": "modify",
      "date": "2013-07-01"
    },
    {
      "code": "C4337",
      "action": "modify",
      "date": "2013-07-08"
    },
    {
      "code": "C4337",
      "action": "modify",
      "date": "2014-08-04"
    },
    {
      "code": "C4337",
      "action": "modify",
      "date": "2014-08-18"
    },
    {
      "code": "C4337",
      "action": "modify",
      "date": "2014-09-22"
    },
    {
      "code": "C4337",
      "action": "modify",
      "date": "2016-04-25"
    },
    {
      "code": "C4337",
      "action": "modify",
      "date": "2016-12-12"
    },
    {
      "code": "C4337",
      "action": "modify",
      "date": "2017-07-31"
    },
    {
      "code": "C4337",
      "action": "modify",
      "date": "2017-09-26"
    },
    {
      "code": "C4337",
      "action": "modify",
      "date": "2018-07-30"
    },
    {
      "code": "C4337",
      "action": "modify",
      "date": "2018-08-27"
    },
    {
      "code": "C4337",
      "action": "modify",
      "date": "2018-08-27"
    },
    {
      "code": "C4337",
      "action": "modify",
      "date": "2018-09-24"
    },
    {
      "code": "C4337",
      "action": "modify",
      "date": "2018-10-29"
    },
    {
      "code": "C4337",
      "action": "modify",
      "date": "2018-10-29"
    },
    {
      "code": "C4337",
      "action": "modify",
      "date": "2018-12-31"
    },
    {
      "code": "C4337",
      "action": "modify",
      "date": "2019-02-25"
    },
    {
      "code": "C4337",
      "action": "modify",
      "date": "2019-03-25"
    },
    {
      "code": "C4337",
      "action": "modify",
      "date": "2019-05-28"
    },
    {
      "code": "C4337",
      "action": "modify",
      "date": "2019-09-30"
    },
    {
      "code": "C4337",
      "action": "modify",
      "date": "2019-10-28"
    },
    {
      "code": "C4337",
      "action": "modify",
      "date": "2019-11-25"
    },
    {
      "code": "C4337",
      "action": "modify",
      "date": "2020-02-24"
    },
    {
      "code": "C4337",
      "action": "modify",
      "date": "2020-04-27"
    },
    {
      "code": "C4337",
      "action": "modify",
      "date": "2020-09-29"
    },
    {
      "code": "C4337",
      "action": "modify",
      "date": "2020-10-26"
    },
    {
      "code": "C4337",
      "action": "modify",
      "date": "2021-02-22"
    },
    {
      "code": "C4337",
      "action": "modify",
      "date": "2021-03-29"
    },
    {
      "code": "C4337",
      "action": "modify",
      "date": "2021-04-26"
    },
    {
      "code": "C4337",
      "action": "modify",
      "date": "2023-02-27"
    },
    {
      "code": "C4337",
      "action": "modify",
      "date": "2023-03-27"
    },
    {
      "code": "C4337",
      "action": "create",
      "date": "2023-05-30"
    },
    {
      "code": "C4337",
      "action": "modify",
      "date": "2023-05-30"
    },
    {
      "code": "C4337",
      "action": "modify",
      "date": "2023-12-26"
    },
    {
      "code": "C4337",
      "action": "modify",
      "date": "2025-03-31"
    }
  ],
  "maps": [
    {
      "type": "Related To",
      "targetName": "9673/3",
      "targetTermType": "PT",
      "targetCode": "morphology",
      "targetTerminology": "GDC"
    },
    {
      "type": "Related To",
      "targetName": "Malignant lymphoma, lymphocytic, intermediate differentiation, diffuse",
      "targetTermType": "PT",
      "targetCode": "primary_diagnosis",
      "targetTerminology": "GDC"
    },
    {
      "type": "Related To",
      "targetName": "Mantle cell lymphoma (Includes all variants blastic, pleomorphic, small cell)",
      "targetTermType": "PT",
      "targetCode": "primary_diagnosis",
      "targetTerminology": "GDC"
    },
    {
      "type": "Related To",
      "targetName": "Mantle cell lymphoma, extranodal and solid organ sites",
      "targetTermType": "PT",
      "targetCode": "C83.19",
      "targetTerminology": "ICD10CM 2017"
    },
    {
      "type": "Related To",
      "targetName": "Mantle cell lymphoma, lymph nodes of multiple sites",
      "targetTermType": "PT",
      "targetCode": "C83.18",
      "targetTerminology": "ICD10CM 2017"
    },
    {
      "type": "Related To",
      "targetName": "Mantle cell lymphoma, unspecified site, extranodal and solid organ sites",
      "targetTermType": "PT",
      "targetCode": "200.40",
      "targetTerminology": "ICD9CM 2014"
    },
    {
      "type": "Related To",
      "targetName": "Mantle cell lymphoma, unspecified site",
      "targetTermType": "PT",
      "targetCode": "C83.10",
      "targetTerminology": "ICD10CM 2017"
    },
    {
      "type": "Has Synonym",
      "targetName": "Mantle cell lymphoma",
      "targetTermType": "PT",
      "targetCode": "200.4",
      "targetTerminology": "ICD9CM 2014"
    },
    {
      "type": "Related To",
      "targetName": "Mantle cell lymphoma",
      "targetTermType": "PT",
      "targetCode": "9673/3",
      "targetTerminology": "ICDO3",
      "targetTerminologyVersion": "3.1"
    },
    {
      "type": "Related To",
      "targetName": "Mantle cell lymphoma",
      "targetTermType": "PT",
      "targetCode": "9673/3",
      "targetTerminology": "ICDO3",
      "targetTerminologyVersion": "3.2"
    },
    {
      "type": "Has Synonym",
      "targetName": "Mantle cell lymphoma",
      "targetTermType": "PT",
      "targetCode": "C83.1",
      "targetTerminology": "ICD10CM 2017"
    },
    {
      "type": "Has Synonym",
      "targetName": "Mantle zone lymphoma",
      "targetTermType": "PT",
      "targetCode": "primary_diagnosis",
      "targetTerminology": "GDC"
    }
  ]
}
