{
  "code": "C7167",
  "name": "Myelodysplastic Syndrome with Excess Blasts-1",
  "terminology": "ncit",
  "version": "25.11d",
  "conceptStatus": "Retired_Concept",
  "leaf": true,
  "active": false,
  "synonyms": [
    {
      "name": "RAEB-1",
      "termType": "SY",
      "type": "FULL_SYN",
      "source": "caDSR"
    },
    {
      "name": "RAEB I",
      "termType": "PT",
      "type": "FULL_SYN",
      "source": "GDC"
    },
    {
      "name": "Refractory anemia with excess of blasts 1",
      "termType": "PT",
      "type": "FULL_SYN",
      "source": "mCode",
      "code": "D46.21",
      "subSource": "ICD-10 CM"
    },
    {
      "name": "MDS-EB-1",
      "termType": "AB",
      "type": "FULL_SYN",
      "source": "NCI"
    },
    {
      "name": "Myelodysplastic Syndrome with Excess Blasts-1",
      "termType": "PT",
      "type": "FULL_SYN",
      "source": "NCI"
    },
    {
      "name": "RAEB-I",
      "termType": "AB",
      "type": "FULL_SYN",
      "source": "NCI"
    },
    {
      "name": "Myelodysplastic Syndrome with Excess Blasts-1",
      "type": "Preferred_Name"
    }
  ],
  "properties": [
    {
      "code": "P310",
      "type": "Concept_Status",
      "value": "Retired_Concept"
    },
    {
      "code": "P322",
      "type": "Contributing_Source",
      "value": "GDC"
    },
    {
      "code": "P322",
      "type": "Contributing_Source",
      "value": "mCode"
    },
    {
      "code": "P98",
      "type": "DesignNote",
      "value": "Thu Mar 30 13:09:30 EDT 2023 - See 'Myelodysplastic Syndrome with Excess Blasts(C7506)'"
    },
    {
      "code": "P366",
      "type": "Legacy Concept Name",
      "value": "RAEB-1"
    },
    {
      "code": "P375",
      "type": "Maps_To",
      "value": "RAEB I"
    },
    {
      "code": "P363",
      "type": "Neoplastic_Status",
      "value": "Malignant"
    },
    {
      "code": "P364",
      "type": "OLD_ASSOCIATION",
      "value": "A32|C177621"
    },
    {
      "code": "P364",
      "type": "OLD_ASSOCIATION",
      "value": "A8|C126659"
    },
    {
      "code": "P364",
      "type": "OLD_ASSOCIATION",
      "value": "A8|C157711"
    },
    {
      "code": "P364",
      "type": "OLD_ASSOCIATION",
      "value": "A8|C177537"
    },
    {
      "code": "P364",
      "type": "OLD_ASSOCIATION",
      "value": "A8|C193006"
    },
    {
      "code": "P364",
      "type": "OLD_ASSOCIATION",
      "value": "A8|C193231"
    },
    {
      "code": "P200",
      "type": "OLD_PARENT",
      "value": "C7506"
    },
    {
      "code": "P106",
      "type": "Semantic_Type",
      "value": "Neoplastic Process"
    }
  ],
  "parents": [
    {
      "code": "C203440",
      "name": "Retired Concept 2023"
    }
  ],
  "history": [
    {
      "code": "C7167",
      "action": "create",
      "date": "2003-08-12"
    },
    {
      "code": "C7167",
      "action": "modify",
      "date": "2003-10-31"
    },
    {
      "code": "C7167",
      "action": "modify",
      "date": "2003-12-30"
    },
    {
      "code": "C7167",
      "action": "modify",
      "date": "2004-03-30"
    },
    {
      "code": "C7167",
      "action": "modify",
      "date": "2004-12-30"
    },
    {
      "code": "C7167",
      "action": "modify",
      "date": "2009-11-23"
    },
    {
      "code": "C7167",
      "action": "modify",
      "date": "2010-03-08"
    },
    {
      "code": "C7167",
      "action": "modify",
      "date": "2013-02-25"
    },
    {
      "code": "C7167",
      "action": "modify",
      "date": "2013-03-04"
    },
    {
      "code": "C7167",
      "action": "modify",
      "date": "2013-03-11"
    },
    {
      "code": "C7167",
      "action": "modify",
      "date": "2013-03-18"
    },
    {
      "code": "C7167",
      "action": "modify",
      "date": "2013-03-25"
    },
    {
      "code": "C7167",
      "action": "modify",
      "date": "2013-04-01"
    },
    {
      "code": "C7167",
      "action": "modify",
      "date": "2013-04-08"
    },
    {
      "code": "C7167",
      "action": "modify",
      "date": "2013-04-15"
    },
    {
      "code": "C7167",
      "action": "modify",
      "date": "2013-04-22"
    },
    {
      "code": "C7167",
      "action": "modify",
      "date": "2013-04-29"
    },
    {
      "code": "C7167",
      "action": "modify",
      "date": "2013-05-06"
    },
    {
      "code": "C7167",
      "action": "modify",
      "date": "2013-05-13"
    },
    {
      "code": "C7167",
      "action": "modify",
      "date": "2013-05-20"
    },
    {
      "code": "C7167",
      "action": "modify",
      "date": "2013-05-28"
    },
    {
      "code": "C7167",
      "action": "modify",
      "date": "2013-06-03"
    },
    {
      "code": "C7167",
      "action": "modify",
      "date": "2013-06-10"
    },
    {
      "code": "C7167",
      "action": "modify",
      "date": "2013-06-17"
    },
    {
      "code": "C7167",
      "action": "modify",
      "date": "2013-06-24"
    },
    {
      "code": "C7167",
      "action": "modify",
      "date": "2013-07-01"
    },
    {
      "code": "C7167",
      "action": "modify",
      "date": "2013-07-08"
    },
    {
      "code": "C7167",
      "action": "modify",
      "date": "2014-02-03"
    },
    {
      "code": "C7167",
      "action": "modify",
      "date": "2016-04-25"
    },
    {
      "code": "C7167",
      "action": "modify",
      "date": "2016-12-05"
    },
    {
      "code": "C7167",
      "action": "modify",
      "date": "2017-08-28"
    },
    {
      "code": "C7167",
      "action": "modify",
      "date": "2017-09-26"
    },
    {
      "code": "C7167",
      "action": "modify",
      "date": "2018-06-25"
    },
    {
      "code": "C7167",
      "action": "modify",
      "date": "2018-06-25"
    },
    {
      "code": "C7167",
      "action": "modify",
      "date": "2018-10-29"
    },
    {
      "code": "C7167",
      "action": "modify",
      "date": "2018-10-29"
    },
    {
      "code": "C7167",
      "action": "modify",
      "date": "2019-09-30"
    },
    {
      "code": "C7167",
      "action": "modify",
      "date": "2020-02-24"
    },
    {
      "code": "C7167",
      "action": "modify",
      "date": "2020-09-29"
    },
    {
      "code": "C7167",
      "action": "modify",
      "date": "2021-02-22"
    },
    {
      "code": "C7167",
      "action": "modify",
      "date": "2021-03-29"
    },
    {
      "code": "C7167",
      "action": "modify",
      "date": "2023-03-27"
    },
    {
      "code": "C7167",
      "action": "merge",
      "date": "2023-04-24",
      "replacementCode": "C7506",
      "replacementName": "Myelodysplastic Syndrome with Excess Blasts"
    },
    {
      "code": "C7167",
      "action": "modify",
      "date": "2023-04-24"
    },
    {
      "code": "C7167",
      "action": "retire",
      "date": "2023-04-24"
    },
    {
      "code": "C7167",
      "action": "modify",
      "date": "2024-01-29"
    },
    {
      "code": "C7167",
      "action": "modify",
      "date": "2024-04-29"
    }
  ],
  "maps": [
    {
      "type": "Has Synonym",
      "targetName": "RAEB I",
      "targetTermType": "PT",
      "targetCode": "primary_diagnosis",
      "targetTerminology": "GDC"
    }
  ]
}
